<?xml version="1.0" encoding="UTF-8" ?>

<!-- 
 * tiles.xml
 *
 * Copyright (C) 2019 Universidad de Sevilla
 * 
 * The use of this project is hereby constrained to the conditions of the 
 * TDG Licence, a copy of which you may download from 
 * http://www.tdg-seville.info/License.html
 -->

<!DOCTYPE tiles-definitions PUBLIC
       "-//Apache Software Foundation//DTD Tiles Configuration 2.0//EN"
       "http://tiles.apache.org/dtds/tiles-config_2_0.dtd">
       
<tiles-definitions>

	<definition name="conference/listForthcoming" extends="master.page">
		<put-attribute name="title" value="Forthcoming conferences" />
		<put-attribute name="body" value="/views/conference/listForthcoming.jsp" />
	</definition>

	<definition name="conference/listPast" extends="master.page">
		<put-attribute name="title" value="Past conferences" />
		<put-attribute name="body" value="/views/conference/listPast.jsp" />
	</definition>

	<definition name="conference/listRunning" extends="master.page">
		<put-attribute name="title" value="Running conferences" />
		<put-attribute name="body" value="/views/conference/listRunning.jsp" />
	</definition>

	<definition name="conference/administrator/listDeadline5Days" extends="master.page">
		<put-attribute name="title" value="Conferences whose submission deadline elapsed in the last five days" />
		<put-attribute name="body" value="/views/conference/listDeadline5Days.jsp" />
	</definition>

	<definition name="conference/administrator/listNotification4Days" extends="master.page">
		<put-attribute name="title" value="Conferences whose notification deadline elapses in less than five days" />
		<put-attribute name="body" value="/views/conference/listNotification4Days.jsp" />
	</definition>

	<definition name="conference/administrator/listCamera4Days" extends="master.page">
		<put-attribute name="title" value="Conferences whose camera-ready deadline elapses in less than five days" />
		<put-attribute name="body" value="/views/conference/listCamera4Days.jsp" />
	</definition>

	<definition name="conference/administrator/listStartNext4Days" extends="master.page">
		<put-attribute name="title" value="Conferences that are going to be organised in less than five days" />
		<put-attribute name="body" value="/views/conference/listStartNext4Days.jsp" />
	</definition>

	<definition name="conference/administrator/listAll" extends="master.page">
		<put-attribute name="title" value="All conferences" />
		<put-attribute name="body" value="/views/conference/listAll.jsp" />
	</definition>

	<definition name="conference/showNotLogged" extends="master.page">
		<put-attribute name="title" value="Conference" />
		<put-attribute name="body" value="/views/conference/showNotLogged.jsp" />
	</definition>

	<definition name="conference/administrator/show" extends="master.page">
		<put-attribute name="title" value="Conference" />
		<put-attribute name="body" value="/views/conference/show.jsp" />
	</definition>

	<definition name="conference/administrator/listConferenceAdminMenu" extends="master.page">
		<put-attribute name="title" value="Conferences lists" />
		<put-attribute name="body" value="/views/conference/listConferenceAdminMenu.jsp" />
	</definition>

	<definition name="conference/administrator/create" extends="master.page">
		<put-attribute name="title" value="Edit" />
		<put-attribute name="body" value="/views/conference/edit.jsp" />
	</definition>

	<definition name="conference/administrator/edit" extends="master.page">
		<put-attribute name="title" value="Edit" />
		<put-attribute name="body" value="/views/conference/edit.jsp" />
	</definition>

</tiles-definitions>